{
    "identityPoolName": "tennisnow3d0e3eb8_identitypool_3d0e3eb8",
    "allowUnauthenticatedIdentities": false,
    "resourceNameTruncated": "tennis3d0e3eb8",
    "userPoolName": "tennisnow3d0e3eb8_userpool_3d0e3eb8",
    "autoVerifiedAttributes": [
        "email"
    ],
    "mfaConfiguration": "OFF",
    "mfaTypes": [
        "SMS Text Message"
    ],
    "smsAuthenticationMessage": "Your authentication code is {####}",
    "smsVerificationMessage": "Your verification code is {####}",
    "emailVerificationSubject": "Your verification code",
    "emailVerificationMessage": "Your verification code is {####}",
    "defaultPasswordPolicy": false,
    "passwordPolicyMinLength": 8,
    "passwordPolicyCharacters": [],
    "requiredAttributes": [
        "email"
    ],
    "userpoolClientGenerateSecret": false,
    "userpoolClientRefreshTokenValidity": 30,
    "userpoolClientWriteAttributes": [
        "email"
    ],
    "userpoolClientReadAttributes": [
        "email"
    ],
    "userpoolClientLambdaRole": "tennis3d0e3eb8_userpoolclient_lambda_role",
    "userpoolClientSetAttributes": false,
    "sharedId": "3d0e3eb8",
    "resourceName": "tennisnow3d0e3eb8",
    "authSelections": "identityPoolAndUserPool",
    "authRoleArn": {
        "Fn::GetAtt": [
            "AuthRole",
            "Arn"
        ]
    },
    "unauthRoleArn": {
        "Fn::GetAtt": [
            "UnauthRole",
            "Arn"
        ]
    },
    "useDefault": "defaultSocial",
    "usernameAttributes": [
        "email"
    ],
    "userPoolGroupList": [],
    "serviceName": "Cognito",
    "dependsOn": [],
    "hostedUI": true,
    "hostedUIDomainName": "tennisnow23b2f9c0-23b2f9c0",
    "authProvidersUserPool": [],
    "hostedUIProviderMeta": "[]",
    "oAuthMetadata": "{\"AllowedOAuthFlows\":[\"code\"],\"AllowedOAuthScopes\":[\"phone\",\"email\",\"openid\",\"profile\",\"aws.cognito.signin.user.admin\"],\"CallbackURLs\":[\"https://beta.tennisnow.net/\",\"http://localhost:3000/\"],\"LogoutURLs\":[\"https://beta.tennisnow.net/\",\"http://localhost:3000/\"]}",
    "authProviders": []
}